{
  "start": "openMainPage",
  "openMainPage": [
    "loginUser",
    "openCreateAccountPage",
    "verifyProductStickerIsDisplayed",
    "openProductDetailsPage",
    "openCampaignProductDetailsPage",
    "addProductToCart",
    "openCartPageByCheckout"
  ],
  "loginUser": [
    "logoutUser",
    "verifyProductStickerIsDisplayed",
    "openProductDetailsPage",
    "openCampaignProductDetailsPage",
    "openCartPageByCheckout"
  ],
  "logoutUser": [],
  "openCreateAccountPage": [
    "fillCreateAccountFields"
  ],
  "fillCreateAccountFields": [
    "verifyCreateAccountSuccessMessage"
  ],
  "verifyCreateAccountSuccessMessage": [
    "loginUser"
  ],
  "verifyProductStickerIsDisplayed": [],
  "openProductDetailsPage": [
    "verifyProductDetails",
    "verifyProductDetailsPageElements",
    "addProductToCart"
  ],
  "openCampaignProductDetailsPage": [
    "verifyProductDetails",
    "verifyProductDetailsPageElements",
    "addProductToCart"
  ],
  "verifyProductDetails": [
    "addProductToCart"
  ],
  "verifyProductDetailsPageElements": [],
  "addProductToCart": [
    "openCartPageByCheckout"
  ],
  "openCartPageByCheckout": [
    "removeAllFromCart"
  ],
  "removeAllFromCart": [
    "verifyCartIsEmpty"
  ],
  "verifyCartIsEmpty": []
}